Workbook

Sheet CRISP-DM
B2: DAY 1 – BUSINESS THINKING + CRISP-DM FOUNDATION
B3: Theme: From Business Problem → Data Analysis Questions
B5: SECTION A – KEY DEFINITIONS & CONCEPTS
B6: Term | C6: Definition / Explanation | D6: Where Excel is typically used
B7: CRISP-DM | C7: Cross-Industry Standard Process for Data Mining. A widely used, structured approach for planning and executing data projects. It has six phases. | D7: Overall process framework – Excel supports almost every phase
B8: Business Understanding | C8: First phase. Focus on understanding the project objectives and requirements from a business perspective, then converting this knowledge into a data mining problem definition. | D8: Documenting objectives, writing problem statements, stakeholder notes
B9: Data Understanding | C9: Second phase. Collect initial data, explore it, identify data quality problems, and discover first insights. | D9: Initial exploration, sorting, filtering, basic charts, summary statistics
B10: Data Preparation | C10: Third phase. Construct the final dataset from the raw data. Includes cleaning, transforming, integrating and formatting data. | D10: Cleaning, formulas, removing duplicates, creating calculated columns
B11: Modeling | C11: Fourth phase. Select and apply modeling techniques, calibrate parameters, and build predictive or descriptive models. | D11: Basic statistical models, what-if analysis, scenario tools (limited)
B12: Evaluation | C12: Fifth phase. Thoroughly evaluate the model and review the steps to ensure it properly achieves the business objectives. | D12: Creating evaluation reports, comparing model results side-by-side
B13: Deployment | C13: Sixth (final) phase. Put the model into practice – generate reports, implement a system, or create dashboards for end users. | D13: Building final management reports, dashboards, and presentation tables
B14: Business Objective | C14: A clear, measurable goal that the organization wants to achieve (e.g., increase customer retention by 10% in 6 months). | D14: Writing the objective clearly in a structured sheet
B15: Data Analysis Question | C15: A specific, answerable question that can be investigated with data to support the business objective. | D15: Listing questions that will guide sorting, filtering and formula work
B16: Problem Statement | C16: A concise description of the issue to be solved, including context, impact, and desired outcome. | D16: Documenting the problem so the whole team stays aligned
B18: SECTION B – CONCEPTUAL QUESTIONS (Write your answers in the yellow cells)
B19: Q1. List the six phases of the CRISP-DM framework in the correct order.
B21: Q2. Why is the Business Understanding phase considered the most critical phase? Explain in 2–3 sentences.
B23: Q3. Give one concrete example of how Excel can be used in the Data Preparation phase.
B25: Q4. What is the difference between a Business Objective and a Data Analysis Question? Provide one example of each.
B27: Q5. A retail company says: “We want to sell more.” Rewrite this vague statement into a clear Business Objective and then into two Data Analysis Questions.
B29: SECTION C – HANDS-ON BUSINESS SCENARIOS (Practice Focus)
B30: For each scenario below: (1) Write a clear Problem Statement, (2) Map which CRISP-DM phases will be most active, (3) Create 2–3 specific Data Analysis Questions.
B31: SCENARIO 1 – Online Fashion Retailer
B32: A mid-size online fashion retailer has noticed that many first-time customers never place a second order. Management wants to understand why and improve the situation. They have order history, customer demographics, product categories, discount usage, and delivery ratings available in Excel.
B33: Problem Statement:
B34: Most relevant CRISP-DM phases:
... B40: A superstore chain operating in four regions (North, South, East, West) has seen overall sales growth, but the South region is lagging. Store managers suspect issues with inventory, promotions, or product mix. They have monthly sales, inventory levels, promotion calendars, and customer footfall data in Excel files.
B41: Problem Statement: | C41: A superstore chain operating in four regions(North, South, East, West), but lagging in the South region. We need to find 1.Reason behind Transportation, 2. Reason behind product mix, 3.What factors are responsible for this.
B42: Most relevant CRISP-DM phases: | C42: Analysis the given excle data file.
B43: Data Analysis Question 1:
B44: Data Analysis Question 2:
B45: Data Analysis Question 3:

Sheet DATA DUMP - I
A1: SAMPLE SALES DATASET – Apex Retail
A3: OrderID | B3: OrderDate | C3: Region | D3: Product | E3: Category | F3: Quantity | G3: cost price[sp-(sp*discount/100)] | H3: UnitPrice | I3: SalesAmount | J3: Rating | K3: CustomerType | L3: Discount% | M3: PaymentMode | N3: Helper 1 | O3: Rating | P3: Profit
A4: ORD-1001 | B4: 2025-10-04 | C4: South | D4: Sticky Notes | E4: Stationery | F4: 2 | G4: =Table1[[#This Row],[SalesAmount]]-(Table1[[#This Row],[SalesAmount]]*Table1[[#This Row],[Discount%]]/100) -> 48633.6 | H4: 199 | I4: 60792 | J4: =IF(Table1[[#This Row],[SalesAmount]]>120000,"H1", IF(AND(Table1[[#This Row],[SalesAmount]]>80000,Table1[[#This Row],[SalesAmount]]<=120000),"H2", IF(AND(Table1[[#This Row],[SalesAmount]]>50000,Table1[[#This Row],[SalesAmount]]<=80000),"H3", IF(AND(Table1[[#This Row],[SalesAmount]]>0,Table1[[#This Row],[SalesAmount]]<=50000),"H4", "L1")))) -> H3 | K4: New | L4: 20 | M4: UPI | N4: =AND(Table1[[#This Row],[PaymentMode]]="CASH ON DELIVERY",Table1[[#This Row],[Category]]="ELECTRONICS") -> FALSE | O4: 2 | P4: =Table1[[#This Row],[SalesAmount]]-Table1[[#This Row],[cost price'[sp-(sp*discount/100)']]] -> 12158.4 | R4: =SUMIF(Table1[Helper 1],"TRUE",Table1[SalesAmount]) -> 66935.7
A5: ORD-1002 | B5: 2025-10-05 | C5: North | D5: Sticky Notes | E5: Stationery | F5: 2 | G5: =Table1[[#This Row],[SalesAmount]]-(Table1[[#This Row],[SalesAmount]]*Table1[[#This Row],[Discount%]]/100) -> 160.38 | H5: 99 | I5: 178.2 | J5: =IF(Table1[[#This Row],[SalesAmount]]>120000,"H1", IF(AND(Table1[[#This Row],[SalesAmount]]>80000,Table1[[#This Row],[SalesAmount]]<=120000),"H2", IF(AND(Table1[[#This Row],[SalesAmount]]>50000,Table1[[#This Row],[SalesAmount]]<=80000),"H3", IF(AND(Table1[[#This Row],[SalesAmount]]>0,Table1[[#This Row],[SalesAmount]]<=50000),"H4", "L1")))) -> H4 | K5: New | L5: 10 | M5: UPI | N5: =AND(Table1[[#This Row],[PaymentMode]]="CASH ON DELIVERY",Table1[[#This Row],[Category]]="ELECTRONICS") -> FALSE | O5: 3 | P5: =Table1[[#This Row],[SalesAmount]]-Table1[[#This Row],[cost price'[sp-(sp*discount/100)']]] -> 17.82 | R5: =AVERAGEIF(Table1[Helper 1],"TRUE",Table1[SalesAmount]) -> 22311.9
A6: ORD-1003 | B6: 2025-12-23 | C6: West | D6: Bookshelf | E6: Furniture | F6: 1 | G6: =Table1[[#This Row],[SalesAmount]]-(Table1[[#This Row],[SalesAmount]]*Table1[[#This Row],[Discount%]]/100) -> 1899 | H6: 1899 | I6: 1899 | J6: =IF(Table1[[#This Row],[SalesAmount]]>120000,"H1", IF(AND(Table1[[#This Row],[SalesAmount]]>80000,Table1[[#This Row],[SalesAmount]]<=120000),"H2", IF(AND(Table1[[#This Row],[SalesAmount]]>50000,Table1[[#This Row],[SalesAmount]]<=80000),"H3", IF(AND(Table1[[#This Row],[SalesAmount]]>0,Table1[[#This Row],[SalesAmount]]<=50000),"H4", "L1")))) -> H4 | K6: New | L6: 0 | M6: Cash on Delivery | N6: =AND(Table1[[#This Row],[PaymentMode]]="CASH ON DELIVERY",Table1[[#This Row],[Category]]="ELECTRONICS") -> FALSE | O6: 4 | P6: =Table1[[#This Row],[SalesAmount]]-Table1[[#This Row],[cost price'[sp-(sp*discount/100)']]] -> 0
A7: ORD-1004 | B7: 2025-12-29 | C7: West | D7: USB-C Hub | E7: Electronics | F7: 1 | G7: =Table1[[#This Row],[SalesAmount]]-(Table1[[#This Row],[SalesAmount]]*Table1[[#This Row],[Discount%]]/100) -> 3499 | H7: 3499 | I7: 3499 | J7: =IF(Table1[[#This Row],[SalesAmount]]>120000,"H1", IF(AND(Table1[[#This Row],[SalesAmount]]>80000,Table1[[#This Row],[SalesAmount]]<=120000),"H2", IF(AND(Table1[[#This Row],[SalesAmount]]>50000,Table1[[#This Row],[SalesAmount]]<=80000),"H3", IF(AND(Table1[[#This Row],[SalesAmount]]>0,Table1[[#This Row],[SalesAmount]]<=50000),"H4", "L1")))) -> H4 | K7: Returning | L7: 0 | M7: Net Banking | N7: =AND(Table1[[#This Row],[PaymentMode]]="CASH ON DELIVERY",Table1[[#This Row],[Category]]="ELECTRONICS") -> FALSE | O7: 3 | P7: =Table1[[#This Row],[SalesAmount]]-Table1[[#This Row],[cost price'[sp-(sp*discount/100)']]] -> 0
A8: ORD-1005 | B8: 2025-11-18 | C8: North | D8: Standing Desk | E8: Furniture | F8: 6 | G8: =Table1[[#This Row],[SalesAmount]]-(Table1[[#This Row],[SalesAmount]]*Table1[[#This Row],[Discount%]]/100) -> 32994 | H8: 5499 | I8: 32994 | J8: =IF(Table1[[#This Row],[SalesAmount]]>120000,"H1", IF(AND(Table1[[#This Row],[SalesAmount]]>80000,Table1[[#This Row],[SalesAmount]]<=120000),"H2", IF(AND(Table1[[#This Row],[SalesAmount]]>50000,Table1[[#This Row],[SalesAmount]]<=80000),"H3", IF(AND(Table1[[#This Row],[SalesAmount]]>0,Table1[[#This Row],[SalesAmount]]<=50000),"H4", "L1")))) -> H4 | K8: Returning | L8: 0 | M8: Net Banking | N8: =AND(Table1[[#This Row],[PaymentMode]]="CASH ON DELIVERY",Table1[[#This Row],[Category]]="ELECTRONICS") -> FALSE | O8: 4 | P8: =Table1[[#This Row],[SalesAmount]]-Table1[[#This Row],[cost price'[sp-(sp*discount/100)']]] -> 0
A9: ORD-1006 | B9: 2025-12-08 | C9: North | D9: USB-C Hub | E9: Electronics | F9: 1 | G9: =Table1[[#This Row],[SalesAmount]]-(Table1[[#This Row],[SalesAmount]]*Table1[[#This Row],[Discount%]]/100) -> 6479.19 | H9: 7999 | I9: 7199.1 | J9: =IF(Table1[[#This Row],[SalesAmount]]>120000,"H1", IF(AND(Table1[[#This Row],[SalesAmount]]>80000,Table1[[#This Row],[SalesAmount]]<=120000),"H2", IF(AND(Table1[[#This Row],[SalesAmount]]>50000,Table1[[#This Row],[SalesAmount]]<=80000),"H3", IF(AND(Table1[[#This Row],[SalesAmount]]>0,Table1[[#This Row],[SalesAmount]]<=50000),"H4", "L1")))) -> H4 | K9: Returning | L9: 10 | M9: Credit Card | N9: =AND(Table1[[#This Row],[PaymentMode]]="CASH ON DELIVERY",Table1[[#This Row],[Category]]="ELECTRONICS") -> FALSE | O9: 4 | P9: =Table1[[#This Row],[SalesAmount]]-Table1[[#This Row],[cost price'[sp-(sp*discount/100)']]] -> 719.91
A10: ORD-1007 | B10: 2025-12-30 | C10: North | D10: Ergonomic Keyboard | E10: Electronics | F10: 6 | G10: =Table1[[#This Row],[SalesAmount]]-(Table1[[#This Row],[SalesAmount]]*Table1[[#This Row],[Discount%]]/100) -> 113994 | H10: 18999 | I10: 113994 | J10: =IF(Table1[[#This Row],[SalesAmount]]>120000,"H1", IF(AND(Table1[[#This Row],[SalesAmount]]>80000,Table1[[#This Row],[SalesAmount]]<=120000),"H2", IF(AND(Table1[[#This Row],[SalesAmount]]>50000,Table1[[#This Row],[SalesAmount]]<=80000),"H3", IF(AND(Table1[[#This Row],[SalesAmount]]>0,Table1[[#This Row],[SalesAmount]]<=50000),"H4", "L1")))) -> H2 | K10: New | L10: 0 | M10: UPI | N10: =AND(Table1[[#This Row],[PaymentMode]]="CASH ON DELIVERY",Table1[[#This Row],[Category]]="ELECTRONICS") -> FALSE | O10: 4 | P10: =Table1[[#This Row],[SalesAmount]]-Table1[[#This Row],[cost price'[sp-(sp*discount/100)']]] -> 0
A11: ORD-1008 | B11: 2025-11-18 | C11: East | D11: Wireless Mouse | E11: Electronics | F11: 4 | G11: =Table1[[#This Row],[SalesAmount]]-(Table1[[#This Row],[SalesAmount]]*Table1[[#This Row],[Discount%]]/100) -> 13996 | H11: 3499 | I11: 13996 | J11: =IF(Table1[[#This Row],[SalesAmount]]>120000,"H1", IF(AND(Table1[[#This Row],[SalesAmount]]>80000,Table1[[#This Row],[SalesAmount]]<=120000),"H2", IF(AND(Table1[[#This Row],[SalesAmount]]>50000,Table1[[#This Row],[SalesAmount]]<=80000),"H3", IF(AND(Table1[[#This Row],[SalesAmount]]>0,Table1[[#This Row],[SalesAmount]]<=50000),"H4", "L1")))) -> H4 | K11: Returning | L11: 0 | M11: Net Banking | N11: =AND(Table1[[#This Row],[PaymentMode]]="CASH ON DELIVERY",Table1[[#This Row],[Category]]="ELECTRONICS") -> FALSE | O11: 3 | P11: =Table1[[#This Row],[SalesAmount]]-Table1[[#This Row],[cost price'[sp-(sp*discount/100)']]] -> 0
A12: ORD-1009 | B12: 2025-11-04 | C12: North | D12: Ballpoint Pens (Pack) | E12: Stationery | F12: 6 | G12: =Table1[[#This Row],[SalesAmount]]-(Table1[[#This Row],[SalesAmount]]*Table1[[#This Row],[Discount%]]/100) -> 1340.16 | H12: 349 | I12: 1675.2 | J12: =IF(Table1[[#This Row],[SalesAmount]]>120000,"H1", IF(AND(Table1[[#This Row],[SalesAmount]]>80000,Table1[[#This Row],[SalesAmount]]<=120000),"H2", IF(AND(Table1[[#This Row],[SalesAmount]]>50000,Table1[[#This Row],[SalesAmount]]<=80000),"H3", IF(AND(Table1[[#This Row],[SalesAmount]]>0,Table1[[#This Row],[SalesAmount]]<=50000),"H4", "L1")))) -> H4 | K12: VIP | L12: 20 | M12: UPI | N12: =AND(Table1[[#This Row],[PaymentMode]]="CASH ON DELIVERY",Table1[[#This Row],[Category]]="ELECTRONICS") -> FALSE | O12: 3 | P12: =Table1[[#This Row],[SalesAmount]]-Table1[[#This Row],[cost price'[sp-(sp*discount/100)']]] -> 335.04
A13: ORD-1010 | B13: 2025-12-21 | C13: South | D13: Office Chair | E13: Furniture | F13: 8 | G13: =Table1[[#This Row],[SalesAmount]]-(Table1[[#This Row],[SalesAmount]]*Table1[[#This Row],[Discount%]]/100) -> 41792.4 | H13: 7999 | I13: 43992 | J13: =IF(Table1[[#This Row],[SalesAmount]]>120000,"H1", IF(AND(Table1[[#This Row],[SalesAmount]]>80000,Table1[[#This Row],[SalesAmount]]<=120000),"H2", IF(AND(Table1[[#This Row],[SalesAmount]]>50000,Table1[[#This Row],[SalesAmount]]<=80000),"H3", IF(AND(Table1[[#This Row],[SalesAmount]]>0,Table1[[#This Row],[SalesAmount]]<=50000),"H4", "L1")))) -> H4 | K13: VIP | L13: 5 | M13: Net Banking | N13: =AND(Table1[[#This Row],[PaymentMode]]="CASH ON DELIVERY",Table1[[#This Row],[Category]]="ELECTRONICS") -> FALSE | O13: 2 | P13: =Table1[[#This Row],[SalesAmount]]-Table1[[#This Row],[cost price'[sp-(sp*discount/100)']]] -> 2199.6
A14: ORD-1011 | B14: 2025-11-04 | C14: North | D14: Standing Desk | E14: Furniture | F14: 1 | G14: =Table1[[#This Row],[SalesAmount]]-(Table1[[#This Row],[SalesAmount]]*Table1[[#This Row],[Discount%]]/100) -> 2429.19 | H14: 2999 | I14: 2699.1 | J14: =IF(Table1[[#This Row],[SalesAmount]]>120000,"H1", IF(AND(Table1[[#This Row],[SalesAmount]]>80000,Table1[[#This Row],[SalesAmount]]<=120000),"H2", IF(AND(Table1[[#This Row],[SalesAmount]]>50000,Table1[[#This Row],[SalesAmount]]<=80000),"H3", IF(AND(Table1[[#This Row],[SalesAmount]]>0,Table1[[#This Row],[SalesAmount]]<=50000),"H4", "L1")))) -> H4 | K14: New | L14: 10 | M14: Net Banking | N14: =AND(Table1[[#This Row],[PaymentMode]]="CASH ON DELIVERY",Table1[[#This Row],[Category]]="ELECTRONICS") -> FALSE | O14: 3 | P14: =Table1[[#This Row],[SalesAmount]]-Table1[[#This Row],[cost price'[sp-(sp*discount/100)']]] -> 269.91
A15: ORD-1012 | B15: 2025-11-28 | C15: South | D15: Sticky Notes | E15: Stationery | F15: 8 | G15: =Table1[[#This Row],[SalesAmount]]-(Table1[[#This Row],[SalesAmount]]*Table1[[#This Row],[Discount%]]/100) -> 28154.88 | H15: 499 | I15: 35193.6 | J15: =IF(Table1[[#This Row],[SalesAmount]]>120000,"H1", IF(AND(Table1[[#This Row],[SalesAmount]]>80000,Table1[[#This Row],[SalesAmount]]<=120000),"H2", IF(AND(Table1[[#This Row],[SalesAmount]]>50000,Table1[[#This Row],[SalesAmount]]<=80000),"H3", IF(AND(Table1[[#This Row],[SalesAmount]]>0,Table1[[#This Row],[SalesAmount]]<=50000),"H4", "L1")))) -> H4 | K15: Returning | L15: 20 | M15: UPI | N15: =AND(Table1[[#This Row],[PaymentMode]]="CASH ON DELIVERY",Table1[[#This Row],[Category]]="ELECTRONICS") -> FALSE | O15: 3 | P15: =Table1[[#This Row],[SalesAmount]]-Table1[[#This Row],[cost price'[sp-(sp*discount/100)']]] -> 7038.72
A16: ORD-1013 | B16: 2025-12-14 | C16: West | D16: Whiteboard Markers | E16: Stationery | F16: 5 | G16: =Table1[[#This Row],[SalesAmount]]-(Table1[[#This Row],[SalesAmount]]*Table1[[#This Row],[Discount%]]/100) -> 400.95 | H16: 99 | I16: 445.5 | J16: =IF(Table1[[#This Row],[SalesAmount]]>120000,"H1", IF(AND(Table1[[#This Row],[SalesAmount]]>80000,Table1[[#This Row],[SalesAmount]]<=120000),"H2", IF(AND(Table1[[#This Row],[SalesAmount]]>50000,Table1[[#This Row],[SalesAmount]]<=80000),"H3", IF(AND(Table1[[#This Row],[SalesAmount]]>0,Table1[[#This Row],[SalesAmount]]<=50000),"H4", "L1")))) -> H4 | K16: Returning | L16: 10 | M16: UPI | N16: =AND(Table1[[#This Row],[PaymentMode]]="CASH ON DELIVERY",Table1[[#This Row],[Category]]="ELECTRONICS") -> FALSE | O16: 3 | P16: =Table1[[#This Row],[SalesAmount]]-Table1[[#This Row],[cost price'[sp-(sp*discount/100)']]] -> 44.55
A17: ORD-1014 | B17: 2025-10-15 | C17: South | D17: Bookshelf | E17: Furniture | F17: 8 | G17: =Table1[[#This Row],[SalesAmount]]-(Table1[[#This Row],[SalesAmount]]*Table1[[#This Row],[Discount%]]/100) -> 10448 | H17: 5499 | I17: 10448 | J17: =IF(Table1[[#This Row],[SalesAmount]]>120000,"H1", IF(AND(Table1[[#This Row],[SalesAmount]]>80000,Table1[[#This Row],[SalesAmount]]<=120000),"H2", IF(AND(Table1[[#This Row],[SalesAmount]]>50000,Table1[[#This Row],[SalesAmount]]<=80000),"H3", IF(AND(Table1[[#This Row],[SalesAmount]]>0,Table1[[#This Row],[SalesAmount]]<=50000),"H4", "L1")))) -> H4 | K17: VIP | L17: 0 | M17: UPI | N17: =AND(Table1[[#This Row],[PaymentMode]]="CASH ON DELIVERY",Table1[[#This Row],[Category]]="ELECTRONICS") -> FALSE | O17: 5 | P17: =Table1[[#This Row],[SalesAmount]]-Table1[[#This Row],[cost price'[sp-(sp*discount/100)']]] -> 0
... A43: ORD-1040 | B43: 2025-12-17 | C43: South | D43: Wireless Mouse | E43: Electronics | F43: 3 | G43: =Table1[[#This Row],[SalesAmount]]-(Table1[[#This Row],[SalesAmount]]*Table1[[#This Row],[Discount%]]/100) -> 80.275 | H43: 2499 | I43: 84.5 | J43: =IF(Table1[[#This Row],[SalesAmount]]>120000,"H1", IF(AND(Table1[[#This Row],[SalesAmount]]>80000,Table1[[#This Row],[SalesAmount]]<=120000),"H2", IF(AND(Table1[[#This Row],[SalesAmount]]>50000,Table1[[#This Row],[SalesAmount]]<=80000),"H3", IF(AND(Table1[[#This Row],[SalesAmount]]>0,Table1[[#This Row],[SalesAmount]]<=50000),"H4", "L1")))) -> H4 | K43: VIP | L43: 5 | M43: Net Banking | N43: =AND(Table1[[#This Row],[PaymentMode]]="CASH ON DELIVERY",Table1[[#This Row],[Category]]="ELECTRONICS") -> FALSE | O43: 3 | P43: =Table1[[#This Row],[SalesAmount]]-Table1[[#This Row],[cost price'[sp-(sp*discount/100)']]] -> 4.225
A44: Total | O44: =SUBTOTAL(109,Table1[Rating]) -> 123

Sheet Sheet1
A1: find total sale, ang .max.min sale for each payment mode given in data using AGG function
A9: Column1 | B9: Column2 | C9: Column3 | D9: Column4 | E9: Column5
B10: Cash on Delivery | C10: Net Banking | D10: UPI | E10: Credit card
A11: sum | C11: =SUBTOTAL(9,'DATA DUMP - I'!I7:I42) -> 958573.65 | D11: =SUBTOTAL(9,'DATA DUMP - I'!I4:I41) -> 1019638.8
A12: avg | C12: =SUBTOTAL(1,'DATA DUMP - I'!I7:I42) -> 26627.046 | D12: =SUBTOTAL(1,'DATA DUMP - I'!I4:I41) -> 26832.6
A13: min | C13: =SUBTOTAL(5,'DATA DUMP - I'!I7:I42) -> 188.1 | D13: =SUBTOTAL(5,'DATA DUMP - I'!I4:I41) -> 178.2
A14: max | C14: =SUBTOTAL(4,'DATA DUMP - I'!I7:I42) -> 129193.2 | D14: =SUBTOTAL(4,'DATA DUMP - I'!I4:I41) -> 129193.2
A18: Calcutate the sum of sales in each region | F18: sumif() | G18: avgerageif()
E19: north | F19: =SUMIF(Table1[Region],"north",Table1[SalesAmount]) -> 608160.85 | G19: =AVERAGEIF(Table1[Region],"north",Table1[SalesAmount]) -> 35774.168
E20: south | F20: =SUMIF(Table1[Region],"south",Table1[SalesAmount]) -> 169416.8 | G20: =AVERAGEIF(Table1[Region],"south",Table1[SalesAmount]) -> 15401.527
E21: east | F21: =SUMIF(Table1[Region],"east",Table1[SalesAmount]) -> 193564.3 | G21: =AVERAGEIF(Table1[Region],"east",Table1[SalesAmount]) -> 32260.717
E22: west | F22: =SUMIF(Table1[Region],"west",Table1[SalesAmount]) -> 50385.4 | G22: =AVERAGEIF(Table1[Region],"west",Table1[SalesAmount]) -> 8397.5667
A25: Calculate the cells of all products whose unit price is greater than 5000 | G25: range | H25: unit_price | I25: sumif()
A30: find the sale of products who have been purchesed using COD and belong to a category of electronics | I30: 66935.7
A34: calculate avg profit earned by each region. Also, calculate the total profit earned in the West region by furniture category | L34: east | M34: =AVERAGEIF(Table1[Region],"EAST",Table1[[Profit ]]) -> 1988.0608
L35: west | M35: =AVERAGEIF(Table1[Region],"WEST",Table1[[Profit ]]) -> 749.79
L36: north | M36: =AVERAGEIF(Table1[Region],"NORTH",Table1[[Profit ]]) -> 2717.3701
L37: south | M37: =AVERAGEIF(Table1[Region],"SOUTH",Table1[[Profit ]]) -> 2223.4318
A43: How many products are affordable
A47: Nested If() :-
B48: name | C48: marks | D48: grade | F48: Grade condition
B49: A | C49: 15 | F49: >16 --> A
B50: B | C50: 14 | F50: 10< marks <= 16---> B
B51: C | C51: 9 | F51: marks <= 10 --> Fail
B52: D | C52: 18
A56: Task - 1
A57: Mark these condition
A58: sale > 120000 -> H1
A59: sale <= 120000, sale > 80000 -> H2
A60: sale <= 80000, sale > 50000 -> H3
A61: sale <50000, sale>0 -> H4
A62: sale < 0 -> L1

Sheet BASIC FORMULAS - QUESTIONS
B2: HANDS-ON PRACTICE TASKS
B5: TASK GROUP 1 – INTERFACE FAMILIARITY
B6: T1. Click on cell G15. What does the Name Box show? What appears in the Formula Bar?
B7: 499
B8: T2. Locate the following on the Ribbon and write the Tab + Group name: (a) Sort & Filter buttons (b) Conditional Formatting (c) Number format drop-down.
B10: T3. Select the entire data range (A3:L43). Turn it into an Excel Table (Ctrl + T). What visual changes do you notice?
B11: We get table design options
B12: TASK GROUP 2 – SORTING PRACTICE
B13: T4. Sort the data by Region (A→Z). Which region appears first? How many orders does it have? (Count the visible rows after sorting or use a filter later.)
B14: East Region - 8
B15: T5. Perform a multi-level sort: Primary = Category (A→Z), Secondary = SalesAmount (Largest to Smallest). Write the first three Product names that appear and their SalesAmount.
B16: Laptop Pro 15, Laptop Pro 15, Ergonomic Keyboard
B17: T6. Sort by Rating (Largest to Smallest) then by Discount% (Largest to Smallest). What is the OrderID of the top row after this sort?
B18: ORD-1021 | C18: 11 | D18: 11
B19: TASK GROUP 3 – FILTERING PRACTICE
B20: T7. Apply AutoFilter. Filter Region = “South”. How many orders remain? What is the total SalesAmount you can see (use status bar or a SUM formula on visible cells)?
B21: 11, Total sale = 483912
B22: T8. Clear previous filter. Apply a custom filter on SalesAmount: greater than 15000. List any three OrderIDs that satisfy the condition.
B23: ORD-1031, ORD-1038, ORD-1034
B24: T9. Filter Category = “Electronics” AND CustomerType = “VIP”. How many rows are left? What is the highest Rating among them?
B25: rows= 6, higest rating = 5 | F25: ORD-1031
B26: T10. Create a custom filter on Discount%: greater than or equal to 10 AND less than or equal to 20. How many orders used a discount in this range?
B27: 22 -> subtotal(function no(counta) , range) | F27: =COUNTA('DATA DUMP - I'!A6:A42) -> 37
B28: T11. Filter PaymentMode = “UPI” and Rating ≥ 4. Write two insights you can draw from the remaining data. | F28: =COUNTA('DATA DUMP - I'!A6:A42) -> 37
B29: We have total 4 orders. catagorys =2 Electronics,2 Furniture. Total sale amount = 299977.6 (subtotal), | F29: =SUBTOTAL(3,'DATA DUMP - I'!A6:A42) -> 37
H30: find total sale, ang .max.min sale for each payment mode given in data using AGG function
D35: =SUBTOTAL(9,'DATA DUMP - I'!I6:I41) -> 958668.6

Sheet BASIC FORMULAS NOTES
B2: DAY 2 – EXCEL INTERFACE + DATA EXPLORATION GUIDE
B3: Theme: Get comfortable with the tool and start exploring data
B5: SECTION A – EXCEL INTERFACE QUICK REFERENCE
B6: Component | C6: Description & Purpose
B7: Ribbon | C7: The long strip at the top containing tabs (Home, Insert, Page Layout, Formulas, Data, Review, View). Each tab has groups of related commands.
B8: Quick Access Toolbar | C8: Small toolbar usually above or below the Ribbon. Contains frequently used commands (Save, Undo, Redo). Can be customized.
B9: Formula Bar | C9: The bar just below the Ribbon that shows the content or formula of the currently selected cell. You can edit formulas here.
B10: Name Box | C10: Left of the Formula Bar. Displays the address of the active cell (e.g., B12) or the name of a named range.
B11: Worksheet / Grid | C11: The main working area made of rows (numbered) and columns (lettered). Intersection of a row and column is a cell.
B12: Status Bar | C12: Bottom of the Excel window. Shows ready status, average/count/sum of selected cells, zoom level, and view shortcuts.
B13: Sheet Tabs | C13: At the bottom. Allow switching between different worksheets in the same workbook.
B15: SECTION B – SORTING CONCEPTS
B16: Term | C16: Explanation
B17: Single-column Sort | C17: Arranging all rows based on the values in one column (A→Z, Z→A, Smallest→Largest, Largest→Smallest).
B18: Multi-column Sort | C18: Sorting by a primary column, then by a secondary column (and optionally more levels) to break ties.
B19: Sort Dialog (Custom Sort) | C19: Found under Data → Sort. Allows adding multiple levels, choosing order, and handling headers.
B20: Important Rule | C20: Always select the entire data range (or click any cell inside a proper Excel Table) before sorting so that rows stay intact.
B22: SECTION C – FILTERING CONCEPTS
B23: Term | C23: Explanation
B24: AutoFilter | C24: The drop-down arrows that appear in the header row after selecting Data → Filter. Allows quick filtering by values, text, numbers or dates.
B25: Custom Filter | C25: Accessed from the filter drop-down → Number/Text Filters → Custom Filter. Lets you set conditions such as “greater than”, “contains”, “between”, etc.
B26: AND / OR in Filters | C26: When using Custom Filter you can combine two conditions with AND (both must be true) or OR (either can be true).
B27: Clear Filter | C27: Data → Clear (or the filter icon → Clear Filter From…). Removes the current filter so all rows reappear.
B28: Best Practice | C28: After filtering, you can copy the visible rows to another sheet if you need a permanent subset for further analysis.
B30: SECTION D – USEFUL KEYBOARD SHORTCUTS (Reference only)
B31: Shortcut | C31: Action
B32: Ctrl + Home | C32: Go to cell A1
B33: Ctrl + End | C33: Go to the last used cell
B34: Ctrl + Arrow keys | C34: Jump to the edge of the current data region
B35: Ctrl + Shift + L | C35: Toggle AutoFilter on/off
B36: Alt + A + S + S | C36: Open the Sort dialog
B37: Ctrl + T | C37: Create an Excel Table from selected data
B38: Ctrl + Z / Ctrl + Y | C38: Undo / Redo

Sheet CONDITIONAL FORMATTING
B2: REPORT MAKING & CONDITIONAL FORMATTING GUIDE
B5: SECTION A – BASIC FORMATTING DEFINITIONS & BEST PRACTICES
B6: Element | C6: Definition & Practical Tip
B7: Alignment | C7: Controls how content sits inside a cell: Left, Center, Right (horizontal) and Top, Middle, Bottom (vertical). Use Center for headers and numbers that need to line up.
B8: Borders | C8: Lines around cells. Use thin borders for data tables and thicker or double borders to separate report sections.
B9: Fonts | C9: Choose a clean professional font (Arial, Calibri). Use bold for headers, regular for data. Avoid more than two font sizes on one report page.
B10: Fill Colors | C10: Background color of cells. Use sparingly – light fills for headers or alternating rows improve readability. Dark fills with white text work well for titles.
B11: Number Formats | C11: Display numbers as Currency (₹), Percentage, Date, etc. Always apply proper number formats so values are easy to read and compare.
B12: Merge & Center | C12: Combine cells for report titles. Use only for titles – never merge data cells that will be sorted or filtered.
B13: Column Width / Row Height | C13: Adjust so that all content is visible without excessive wrapping. Double-click the column boundary to auto-fit.
B15: SECTION B – STRUCTURED REPORT PRINCIPLES
B16: 1. Title – Clear report name + period + company name at the top.
B17: 2. Context – One or two lines explaining what the report shows and for whom.
B18: 3. Key Metrics – Summary numbers (total sales, average order value, etc.) placed near the top.
B19: 4. Data Table – Cleanly formatted table with headers, consistent alignment and number formats.
B20: 5. Highlights – Conditional formatting or icons that draw attention to important values.
B21: 6. Footer – Source of data, prepared by, date of preparation.
B23: SECTION C – CONDITIONAL FORMATTING CONCEPTS
B24: Feature | C24: What it does & when to use it
B25: Highlight Cell Rules | C25: Pre-defined rules such as Greater Than, Less Than, Between, Equal To, Text that Contains. Quickly flag values that meet a condition.
B26: Top/Bottom Rules | C26: Highlight the Top 10 items, Bottom 10%, Above Average, Below Average, etc. Useful for spotting best and worst performers.
B27: Data Bars | C27: Horizontal bars inside cells that visually represent the magnitude of the value. Great for comparing numbers at a glance.
B28: Color Scales | C28: Cells are colored on a gradient (e.g., red-yellow-green) according to their value. Helps see distribution quickly.
B29: Icon Sets | C29: Arrows, traffic lights, stars, etc. that appear based on value thresholds. Use sparingly for executive reports.
B30: Formula-based Rules | C30: Advanced: write a formula that returns TRUE/FALSE to decide whether the format is applied. Gives maximum flexibility.
B31: Manage Rules | C31: Home → Conditional Formatting → Manage Rules. Review, edit, delete or change the order of existing rules.

Sheet DATA DUMP - II
A1: RAW DATA DUMP – Monthly Regional Performance
A3: Month | B3: Region | C3: StoreID | D3: Category | E3: UnitsSold | F3: Revenue | G3: Target | H3: Achievement% | I3: Returns | J3: CustomerSatisfaction
A4: Jan-2026 | B4: North | C4: N-01 | D4: Electronics | E4: 143 | F4: 1392534 | G4: 1295099 | H4: 107.5 | I4: 5 | J4: 3.6
A5: Jan-2026 | B5: North | C5: N-01 | D5: Furniture | E5: 74 | F5: 200466 | G5: 195524 | H5: 102.5 | I5: 6 | J5: 4.1
A6: Jan-2026 | B6: North | C6: N-01 | D6: Stationery | E6: 219 | F6: 93075 | G6: 90094 | H6: 103.3 | I6: 19 | J6: 4
A7: Jan-2026 | B7: North | C7: N-02 | D7: Electronics | E7: 147 | F7: 1036350 | G7: 1209468 | H7: 85.7 | I7: 11 | J7: 4.6
A8: Jan-2026 | B8: North | C8: N-02 | D8: Furniture | E8: 214 | F8: 800574 | G8: 757089 | H8: 105.7 | I8: 21 | J8: 3.5
A9: Jan-2026 | B9: North | C9: N-02 | D9: Stationery | E9: 185 | F9: 59755 | G9: 57759 | H9: 103.5 | I9: 22 | J9: 4.1
A10: Jan-2026 | B10: South | C10: S-01 | D10: Electronics | E10: 62 | F10: 693408 | G10: 677149 | H10: 102.4 | I10: 0 | J10: 3.7
A11: Jan-2026 | B11: South | C11: S-01 | D11: Furniture | E11: 41 | F11: 224803 | G11: 216065 | H11: 104 | I11: 4 | J11: 3.3
A12: Jan-2026 | B12: South | C12: S-01 | D12: Stationery | E12: 172 | F12: 43172 | G12: 46242 | H12: 93.4 | I12: 1 | J12: 3.8
A13: Jan-2026 | B13: South | C13: S-02 | D13: Electronics | E13: 95 | F13: 582730 | G13: 669559 | H13: 87 | I13: 7 | J13: 4.2
A14: Jan-2026 | B14: South | C14: S-02 | D14: Furniture | E14: 85 | F14: 520370 | G14: 571413 | H14: 91.1 | I14: 0 | J14: 3.4
A15: Jan-2026 | B15: South | C15: S-02 | D15: Stationery | E15: 83 | F15: 32536 | G15: 35359 | H15: 92 | I15: 6 | J15: 3.3
... A75: Mar-2026 | B75: West | C75: W-02 | D75: Stationery | E75: 44 | F75: 23804 | G75: 26723 | H75: 89.1 | I75: 2 | J75: 4.5
A76: Total records: 72 | Data covers 3 months × 4 regions × 2 stores × 3 categories

Sheet CF - QUESTIONS
B2: HANDS-ON REPORT & CONDITIONAL FORMATTING PRACTICE
B5: TASK 1 – BASIC FORMATTING (Apply on a copy of the raw data or a new sheet)
B6: 1.1 Create a professional title at the top: “Apex Retail – Regional Performance Report | Q1 2026”. Merge cells, apply dark blue fill, white bold font, size 16.
B7: 1.2 Add a subtitle line with: Prepared for: Management Team | Data Period: Jan–Mar 2026 | Prepared on: [today’s date].
B8: 1.3 Format the header row of the data table: bold, white text, dark blue fill, center alignment, thin borders.
B9: 1.4 Apply currency format (₹) to Revenue and Target columns. Apply 0.0% format to Achievement% column.
B10: 1.5 Set consistent column widths so that all headers and data are fully visible. Center-align Region, StoreID, Category, UnitsSold, Returns, CustomerSatisfaction.
B11: 1.6 Add light gray alternating row colors (or use Excel Table style) to improve readability of the data table.
B12: 1.7 Add a thin border around the entire data range.
B15: TASK 2 – BUILD A STRUCTURED ONE-PAGE REPORT
B16: 2.1 Above the data table, create a “Key Metrics” summary section with at least these four metrics (use SUM / AVERAGE formulas or values you calculate): • Total Revenue • Average Achievement % • Total Units Sold • Average Customer Satisfaction
B17: 2.2 Give the Key Metrics section a light green fill and clear labels. Format the numbers appropriately.
... B28: 3.6 (Optional challenge) Create a formula-based rule that highlights an entire row if Returns > 15. (Use Manage Rules → New Rule → Use a formula).

Sheet Sheet2
B3: Apex Retail – Regional Performance Report | Q1 2026
B4: Prepared for: Management Team | Data Period: Jan–Mar 2026 | Prepared on: 06-08-2026.
B5: Month | C5: Region | D5: StoreID | E5: Category | F5: UnitsSold | G5: Revenue | H5: Target | I5: Achievement% | J5: Returns | K5: CustomerSatisfaction
B6: Jan-2026 | C6: North | D6: N-01 | E6: Electronics | F6: 143 | G6: 1392534 | H6: 1295099 | I6: 107.5 | J6: 5 | K6: 3.6
B7: Jan-2026 | C7: North | D7: N-01 | E7: Furniture | F7: 74 | G7: 200466 | H7: 195524 | I7: 102.5 | J7: 6 | K7: 4.1
B8: Jan-2026 | C8: North | D8: N-01 | E8: Stationery | F8: 219 | G8: 93075 | H8: 90094 | I8: 103.3 | J8: 19 | K8: 4
B9: Jan-2026 | C9: North | D9: N-02 | E9: Electronics | F9: 147 | G9: 1036350 | H9: 1209468 | I9: 85.7 | J9: 11 | K9: 4.6
B10: Jan-2026 | C10: North | D10: N-02 | E10: Furniture | F10: 214 | G10: 800574 | H10: 757089 | I10: 105.7 | J10: 21 | K10: 3.5
B11: Jan-2026 | C11: North | D11: N-02 | E11: Stationery | F11: 185 | G11: 59755 | H11: 57759 | I11: 103.5 | J11: 22 | K11: 4.1
B12: Jan-2026 | C12: South | D12: S-01 | E12: Electronics | F12: 62 | G12: 693408 | H12: 677149 | I12: 102.4 | J12: 0 | K12: 3.7
B13: Jan-2026 | C13: South | D13: S-01 | E13: Furniture | F13: 41 | G13: 224803 | H13: 216065 | I13: 104 | J13: 4 | K13: 3.3
B14: Jan-2026 | C14: South | D14: S-01 | E14: Stationery | F14: 172 | G14: 43172 | H14: 46242 | I14: 93.4 | J14: 1 | K14: 3.8
B15: Jan-2026 | C15: South | D15: S-02 | E15: Electronics | F15: 95 | G15: 582730 | H15: 669559 | I15: 87 | J15: 7 | K15: 4.2
B16: Jan-2026 | C16: South | D16: S-02 | E16: Furniture | F16: 85 | G16: 520370 | H16: 571413 | I16: 91.1 | J16: 0 | K16: 3.4
B17: Jan-2026 | C17: South | D17: S-02 | E17: Stationery | F17: 83 | G17: 32536 | H17: 35359 | I17: 92 | J17: 6 | K17: 3.3
... B77: Mar-2026 | C77: West | D77: W-02 | E77: Stationery | F77: 44 | G77: 23804 | H77: 26723 | I77: 89.1 | J77: 2 | K77: 4.5

Sheet DAILY ASSIGNMENT
B2: MIXED PRACTICE QUESTIONS
B5: Q1 : Name the six phases of CRISP-DM in the correct sequence. For each phase write one short activity that an analyst might perform in Excel.
B7: Q2 : A hospital administrator says: “We need to reduce patient waiting time.” Convert this into (a) a clear Business Objective and (b) three Data Analysis Questions that could be answered with data.
B9: Q3 : Why should the Evaluation phase come before Deployment? Explain with a simple example related to a sales forecasting report.
B11: Q4 : Describe the difference between sorting and filtering. When would you use both on the same dataset?
B13: Q5 : You need to find all orders from the West region where SalesAmount is between ₹10,000 and ₹25,000 and the customer is a VIP. Write the exact filter steps you would follow.
B15: Q6 : After applying a multi-level sort (Region then Category then SalesAmount descending), the first row shows OrderID ORD-1025. What does this tell you about that order relative to others?
B17: Q7 : List three things you can discover about a dataset only by using the Status Bar after selecting a numeric column.
B19: Q8 : Explain why it is considered bad practice to merge cells inside a data table that will later be sorted or filtered.
B21: Q9 : You want to draw attention to under-performing stores (Achievement% < 85%). Which Conditional Formatting feature would you choose and why?
B23: Q10 : Describe the visual difference between Data Bars and Color Scales. When is each more useful in a management report?
B25: Q11 (Mixed): A manager asks for a one-page report showing only the South region’s performance with high returns highlighted. Outline the sequence of Excel steps (filter → format → conditional format → summary) you would take.
B27: Q12 (Mixed): You have finished a report. Before sending it, list five quality checks you should perform (related to formatting, numbers, filters, and clarity).
